asyncio_pause/__init__.py
asyncio_pause/tests/__init__.py
asyncio_pause/tests/test_pause.py
asyncio_pause-0.5.dist-info/LICENSE.txt
asyncio_pause-0.5.dist-info/METADATA
asyncio_pause-0.5.dist-info/WHEEL
asyncio_pause-0.5.dist-info/top_level.txt
asyncio_pause-0.5.dist-info/RECORD
