Metadata-Version: 2.1
Name: asyncio-pause
Version: 0.5
Summary: A timestamp-based sleep function for Python using asyncio.
Home-page: https://github.com/iAbadia/python-asyncio-pause
Author: Jeremy Gillick - Inaki Abadia
Author-email: none@none.com
License: LICENSE.txt
Keywords: sleep timestamp datetime asyncio
Platform: osx
Platform: posix
Platform: linux
Platform: windows
Classifier: Development Status :: 5 - Production/Stable
Classifier: License :: OSI Approved :: MIT License
Classifier: Natural Language :: English
Classifier: Programming Language :: Python :: 2.6
Classifier: Programming Language :: Python :: 2.7
Classifier: Operating System :: MacOS :: MacOS X
Classifier: Operating System :: POSIX
Classifier: Environment :: Console
License-File: LICENSE.txt
